django_laterpay-2.0.0.dist-info/DESCRIPTION.rst
django_laterpay-2.0.0.dist-info/METADATA
django_laterpay-2.0.0.dist-info/RECORD
django_laterpay-2.0.0.dist-info/WHEEL
django_laterpay-2.0.0.dist-info/metadata.json
django_laterpay-2.0.0.dist-info/top_level.txt
djlaterpay/__init__.py
djlaterpay/middleware.py
