Metadata-Version: 2.0
Name: django-laterpay
Version: 2.0.0
Summary: LaterPay Django tools
Home-page: https://github.com/laterpay/django-laterpay
Author: LaterPay GmbH
Author-email: support@laterpay.net
License: MIT
Keywords: LaterPay API client Django
Platform: UNKNOWN
Classifier: Development Status :: 5 - Production/Stable
Classifier: Environment :: Web Environment
Classifier: Framework :: Django :: 1.8
Classifier: Framework :: Django :: 1.9
Classifier: Framework :: Django :: 1.10
Classifier: Framework :: Django
Classifier: Intended Audience :: Developers
Classifier: License :: OSI Approved :: MIT License
Classifier: Operating System :: OS Independent
Classifier: Programming Language :: Python
Classifier: Programming Language :: Python :: 2
Classifier: Programming Language :: Python :: 2.7
Classifier: Programming Language :: Python :: 3
Classifier: Programming Language :: Python :: 3.4
Classifier: Programming Language :: Python :: 3.5
Classifier: Topic :: Software Development :: Libraries :: Python Modules
Requires-Dist: laterpay-client (>=4.1)
Requires-Dist: Django (>=1.8)
